setup.cfg
setup.py
kyleip/__init__.py
kyleip.egg-info/PKG-INFO
kyleip.egg-info/SOURCES.txt
kyleip.egg-info/dependency_links.txt
kyleip.egg-info/requires.txt
kyleip.egg-info/top_level.txt