Metadata-Version: 1.1
Name: kyleip
Version: 0.2
Summary: The kyleip project
Home-page: https://github.com/kyle38459/kyleip
Author: UNKNOWN
Author-email: UNKNOWN
License: UNKNOWN
Download-URL: https://github.com/kyle38459/kyleip/archive/0.1.tar.gz
Keywords: testing,logging,ip
Platform: UNKNOWN
